datalad_ukbiobank/__init__.py
datalad_ukbiobank/_version.py
datalad_ukbiobank/conftest.py
datalad_ukbiobank/init.py
datalad_ukbiobank/ukb2bids.py
datalad_ukbiobank/ukb2bids_map.py
datalad_ukbiobank/update.py
datalad_ukbiobank/tests/__init__.py
datalad_ukbiobank/tests/test_init.py
datalad_ukbiobank/tests/test_update.py
datalad_ukbiobank-0.3.4.dist-info/LICENSE
datalad_ukbiobank-0.3.4.dist-info/METADATA
datalad_ukbiobank-0.3.4.dist-info/WHEEL
datalad_ukbiobank-0.3.4.dist-info/entry_points.txt
datalad_ukbiobank-0.3.4.dist-info/top_level.txt
datalad_ukbiobank-0.3.4.dist-info/RECORD
