Metadata-Version: 2.1
Name: datalad-ukbiobank
Version: 0.3.4
Summary: DataLad support the UKBiobank
Home-page: https://github.com/datalad/ukbiobank
Author: Michael Hanke
Author-email: michael.hanke@gmail.com
License: MIT
Platform: UNKNOWN
Classifier: Programming Language :: Python
Classifier: License :: OSI Approved :: BSD License
Classifier: Programming Language :: Python :: 3
Requires-Python: >=3.7
License-File: LICENSE
Requires-Dist: datalad (>=0.17.0)
Provides-Extra: devel
Requires-Dist: pytest ; extra == 'devel'
Requires-Dist: pytest-cov ; extra == 'devel'
Requires-Dist: coverage ; extra == 'devel'
